<edges><edge from="dublin" to="tullamore" length="737.7587681620598" speed="10" numLanes="1" id="edge_0" /><edge from="dublin" to="roscommon" length="1339.9466407286523" speed="10" numLanes="1" id="edge_1" /><edge from="dublin" to="portlaoise" length="782.5803473126578" speed="10" numLanes="1" id="edge_2" /><edge from="dublin" to="clonmel" length="1528.0111256139467" speed="10" numLanes="2" id="edge_3" /><edge from="dublin" to="navan" length="450.7238622482728" speed="10" numLanes="1" id="edge_4" /><edge from="antrim" to="tralee" length="3774.096580640193" speed="10" numLanes="2" id="edge_5" /><edge from="antrim" to="letterkenny" length="992.0126007264222" speed="10" numLanes="1" id="edge_6" /><edge from="antrim" to="cork" length="3786.418096301569" speed="10" numLanes="1" id="edge_7" /><edge from="antrim" to="carrick" length="1473.1137091209218" speed="10" numLanes="1" id="edge_8" /><edge from="antrim" to="limerick" length="2964.068993798896" speed="10" numLanes="1" id="edge_9" /><edge from="antrim" to="cavan" length="1048.3711174960897" speed="10" numLanes="1" id="edge_10" /><edge from="antrim" to="waterford" length="3084.0239947185883" speed="10" numLanes="1" id="edge_11" /><edge from="antrim" to="clonmel" length="3016.693885696724" speed="10" numLanes="1" id="edge_12" /><edge from="craigavon" to="tullamore" length="1540.397675926577" speed="10" numLanes="1" id="edge_13" /><edge from="craigavon" to="ennis" length="2570.4116401852834" speed="10" numLanes="1" id="edge_14" /><edge from="craigavon" to="longford" length="1159.4658252833501" speed="10" numLanes="1" id="edge_15" /><edge from="craigavon" to="portlaoise" length="1857.8743229831236" speed="10" numLanes="1" id="edge_16" /><edge from="craigavon" to="belfast" length="401.3776276774778" speed="10" numLanes="1" id="edge_17" /><edge from="carlow" to="monaghan" length="1814.6616764565233" speed="10" numLanes="2" id="edge_18" /><edge from="carlow" to="ennis" length="1406.2805552236011" speed="10" numLanes="1" id="edge_19" /><edge from="carlow" to="dublin" length="800.7558928912107" speed="10" numLanes="1" id="edge_20" /><edge from="carlow" to="cork" length="1567.8698925612418" speed="10" numLanes="1" id="edge_21" /><edge from="cavan" to="carlow" length="1497.416441742243" speed="10" numLanes="1" id="edge_22" /><edge from="cavan" to="tralee" length="2726.8958542635983" speed="10" numLanes="1" id="edge_23" /><edge from="cavan" to="longford" length="455.51728836565576" speed="10" numLanes="1" id="edge_24" /><edge from="cavan" to="wexford" length="2139.5761262455703" speed="10" numLanes="1" id="edge_25" /><edge from="cavan" to="cork" length="2770.1624501101014" speed="10" numLanes="1" id="edge_26" /><edge from="ennis" to="naas" length="1658.5029394004703" speed="10" numLanes="1" id="edge_27" /><edge from="ennis" to="belfast" length="2951.616506255513" speed="10" numLanes="1" id="edge_28" /><edge from="ennis" to="limerick" length="363.6289317422364" speed="10" numLanes="1" id="edge_29" /><edge from="ennis" to="tullamore" length="1225.3411769788854" speed="10" numLanes="1" id="edge_30" /><edge from="ennis" to="monaghan" length="2217.0367610844887" speed="10" numLanes="3" id="edge_31" /><edge from="ennis" to="tralee" length="865.3323061113574" speed="10" numLanes="1" id="edge_32" /><edge from="ennis" to="athlone" length="1082.6823172103625" speed="10" numLanes="1" id="edge_33" /><edge from="ennis" to="letterkenny" length="2740.429893283169" speed="10" numLanes="1" id="edge_34" /><edge from="cork" to="limerick" length="959.5566684672667" speed="10" numLanes="1" id="edge_35" /><edge from="derry" to="cavan" length="1253.186737880672" speed="10" numLanes="1" id="edge_36" /><edge from="derry" to="ennis" length="2904.2703042244534" speed="10" numLanes="1" id="edge_37" /><edge from="derry" to="monaghan" length="948.0854391878403" speed="10" numLanes="1" id="edge_38" /><edge from="derry" to="roscommon" length="1748.785292710343" speed="10" numLanes="3" id="edge_39" /><edge from="derry" to="cork" length="3961.7896208658026" speed="10" numLanes="1" id="edge_40" /><edge from="derry" to="limerick" length="3049.5461957478196" speed="10" numLanes="2" id="edge_41" /><edge from="derry" to="castlebar" length="1943.6939059430115" speed="10" numLanes="1" id="edge_42" /><edge from="derry" to="wexford" length="3377.21201584976" speed="10" numLanes="1" id="edge_43" /><edge from="derry" to="athlone" length="1952.5432133502193" speed="10" numLanes="1" id="edge_44" /><edge from="letterkenny" to="monaghan" length="977.658427059267" speed="10" numLanes="2" id="edge_45" /><edge from="letterkenny" to="clonmel" length="3196.2379448345205" speed="10" numLanes="1" id="edge_46" /><edge from="letterkenny" to="castlebar" length="1715.726085364444" speed="10" numLanes="1" id="edge_47" /><edge from="letterkenny" to="athlone" length="1847.1938176596414" speed="10" numLanes="1" id="edge_48" /><edge from="letterkenny" to="tralee" length="3582.4734472149266" speed="10" numLanes="1" id="edge_49" /><edge from="letterkenny" to="navan" length="1767.3780014473418" speed="10" numLanes="1" id="edge_50" /><edge from="letterkenny" to="enniskillen" length="751.9421520303274" speed="10" numLanes="1" id="edge_51" /><edge from="belfast" to="roscommon" length="1842.3517579441773" speed="10" numLanes="1" id="edge_52" /><edge from="belfast" to="bray" length="1699.7955759443546" speed="10" numLanes="1" id="edge_53" /><edge from="belfast" to="carrick" length="1577.7277965479343" speed="10" numLanes="1" id="edge_54" /><edge from="belfast" to="monaghan" length="773.4623455605321" speed="10" numLanes="1" id="edge_55" /><edge from="belfast" to="sligo" length="1671.5561611863359" speed="10" numLanes="1" id="edge_56" /><edge from="belfast" to="navan" length="1230.0508119585954" speed="10" numLanes="1" id="edge_57" /><edge from="enniskillen" to="kilkenny" length="2117.6368904984633" speed="10" numLanes="1" id="edge_58" /><edge from="enniskillen" to="belfast" length="1084.7363735027973" speed="10" numLanes="2" id="edge_59" /><edge from="enniskillen" to="carrick" length="582.7538073663698" speed="10" numLanes="1" id="edge_60" /><edge from="enniskillen" to="derry" length="833.7247747308461" speed="10" numLanes="1" id="edge_61" /><edge from="enniskillen" to="antrim" length="934.285823503707" speed="10" numLanes="1" id="edge_62" /><edge from="enniskillen" to="cork" length="3128.1694327513655" speed="10" numLanes="1" id="edge_63" /><edge from="enniskillen" to="carlow" length="1963.6588298378108" speed="10" numLanes="1" id="edge_64" /><edge from="enniskillen" to="omagh" length="336.78776699874356" speed="10" numLanes="1" id="edge_65" /><edge from="enniskillen" to="sligo" length="588.6229693105767" speed="10" numLanes="2" id="edge_66" /><edge from="enniskillen" to="portlaoise" length="1716.613526685608" speed="10" numLanes="1" id="edge_67" /><edge from="enniskillen" to="naas" length="1574.0155653614104" speed="10" numLanes="1" id="edge_68" /><edge from="enniskillen" to="roscommon" length="930.686305905486" speed="10" numLanes="1" id="edge_69" /><edge from="enniskillen" to="castlebar" length="1309.0" speed="10" numLanes="1" id="edge_70" /><edge from="galway" to="derry" length="2424.7061677654883" speed="10" numLanes="1" id="edge_71" /><edge from="galway" to="antrim" length="2519.866861562333" speed="10" numLanes="1" id="edge_72" /><edge from="galway" to="naas" length="1619.5264740040527" speed="10" numLanes="1" id="edge_73" /><edge from="galway" to="longford" length="1054.552511731872" speed="10" numLanes="1" id="edge_74" /><edge from="galway" to="kilkenny" length="1445.98789759804" speed="10" numLanes="1" id="edge_75" /><edge from="tralee" to="monaghan" length="3080.839495981574" speed="10" numLanes="2" id="edge_76" /><edge from="tralee" to="sligo" length="2620.7395902683656" speed="10" numLanes="1" id="edge_77" /><edge from="tralee" to="cavan" length="2726.8958542635983" speed="10" numLanes="1" id="edge_78" /><edge from="naas" to="enniskillen" length="1574.0155653614104" speed="10" numLanes="1" id="edge_79" /><edge from="naas" to="letterkenny" length="2307.855281424726" speed="10" numLanes="1" id="edge_80" /><edge from="naas" to="roscommon" length="1203.6760361492622" speed="10" numLanes="2" id="edge_81" /><edge from="naas" to="tullamore" length="506.9921103922624" speed="10" numLanes="1" id="edge_82" /><edge from="kilkenny" to="athlone" length="1092.2069400988075" speed="10" numLanes="2" id="edge_83" /><edge from="kilkenny" to="ennis" length="1231.4369655000617" speed="10" numLanes="1" id="edge_84" /><edge from="kilkenny" to="carlow" length="274.4485379811669" speed="10" numLanes="1" id="edge_85" /><edge from="kilkenny" to="castlebar" length="2034.23622030481" speed="10" numLanes="2" id="edge_86" /><edge from="kilkenny" to="waterford" length="532.124045688597" speed="10" numLanes="1" id="edge_87" /><edge from="kilkenny" to="longford" length="1398.7287085064065" speed="10" numLanes="1" id="edge_88" /><edge from="kilkenny" to="dublin" length="1069.62423308375" speed="10" numLanes="1" id="edge_89" /><edge from="kilkenny" to="cork" length="1294.0208653650063" speed="10" numLanes="1" id="edge_90" /><edge from="kilkenny" to="bray" length="1035.9613892418963" speed="10" numLanes="1" id="edge_91" /><edge from="portlaoise" to="clonmel" length="809.0747802273903" speed="10" numLanes="1" id="edge_92" /><edge from="portlaoise" to="waterford" length="929.1393867445294" speed="10" numLanes="1" id="edge_93" /><edge from="portlaoise" to="longford" length="1010.7353758526511" speed="10" numLanes="1" id="edge_94" /><edge from="portlaoise" to="derry" length="2521.115824392049" speed="10" numLanes="1" id="edge_95" /><edge from="portlaoise" to="wexford" length="967.4378533011824" speed="10" numLanes="1" id="edge_96" /><edge from="carrick" to="wexford" length="2302.0026064277163" speed="10" numLanes="1" id="edge_97" /><edge from="carrick" to="clonmel" length="1987.944164205826" speed="10" numLanes="1" id="edge_98" /><edge from="carrick" to="dundalk" length="1120.0723190937272" speed="10" numLanes="1" id="edge_99" /><edge from="carrick" to="waterford" length="2248.4883811129644" speed="10" numLanes="2" id="edge_100" /><edge from="carrick" to="belfast" length="1577.7277965479343" speed="10" numLanes="1" id="edge_101" /><edge from="carrick" to="letterkenny" length="1244.598328779209" speed="10" numLanes="1" id="edge_102" /><edge from="carrick" to="limerick" length="1668.0938223013716" speed="10" numLanes="1" id="edge_103" /><edge from="carrick" to="longford" length="350.2370625733376" speed="10" numLanes="1" id="edge_104" /><edge from="limerick" to="omagh" length="2554.8857117295875" speed="10" numLanes="1" id="edge_105" /><edge from="limerick" to="tullamore" length="1141.862075734193" speed="10" numLanes="3" id="edge_106" /><edge from="limerick" to="naas" length="1495.9445176877382" speed="10" numLanes="1" id="edge_107" /><edge from="limerick" to="tralee" length="881.4000226911728" speed="10" numLanes="1" id="edge_108" /><edge from="limerick" to="belfast" length="2974.460959568977" speed="10" numLanes="1" id="edge_109" /><edge from="limerick" to="cavan" length="1918.9916623060144" speed="10" numLanes="1" id="edge_110" /><edge from="limerick" to="waterford" length="1188.821685535724" speed="10" numLanes="1" id="edge_111" /><edge from="limerick" to="wexford" length="1536.8932949297423" speed="10" numLanes="1" id="edge_112" /><edge from="limerick" to="kilkenny" length="941.0" speed="10" numLanes="1" id="edge_113" /><edge from="limerick" to="bray" length="1840.928298440762" speed="10" numLanes="1" id="edge_114" /><edge from="longford" to="monaghan" length="803.801592434352" speed="10" numLanes="1" id="edge_115" /><edge from="longford" to="portlaoise" length="1010.7353758526511" speed="10" numLanes="2" id="edge_116" /><edge from="longford" to="castlebar" length="1062.9793036555322" speed="10" numLanes="2" id="edge_117" /><edge from="longford" to="dundalk" length="943.7669203781196" speed="10" numLanes="1" id="edge_118" /><edge from="dundalk" to="dublin" length="816.6382307974566" speed="10" numLanes="1" id="edge_119" /><edge from="dundalk" to="roscommon" length="1265.2339704576384" speed="10" numLanes="2" id="edge_120" /><edge from="dundalk" to="carrick" length="1120.0723190937272" speed="10" numLanes="1" id="edge_121" /><edge from="dundalk" to="clonmel" length="2195.4498400100147" speed="10" numLanes="1" id="edge_122" /><edge from="dundalk" to="carlow" length="1527.0415842405864" speed="10" numLanes="2" id="edge_123" /><edge from="castlebar" to="waterford" length="2513.619104001241" speed="10" numLanes="1" id="edge_124" /><edge from="castlebar" to="letterkenny" length="1715.726085364444" speed="10" numLanes="1" id="edge_125" /><edge from="castlebar" to="belfast" length="2380.462140005591" speed="10" numLanes="1" id="edge_126" /><edge from="castlebar" to="derry" length="1943.6939059430115" speed="10" numLanes="1" id="edge_127" /><edge from="castlebar" to="portlaoise" length="1760.176411613336" speed="10" numLanes="1" id="edge_128" /><edge from="castlebar" to="omagh" length="1597.9127009946444" speed="10" numLanes="1" id="edge_129" /><edge from="castlebar" to="dundalk" length="1953.6839560174517" speed="10" numLanes="1" id="edge_130" /><edge from="castlebar" to="roscommon" length="777.7634601856788" speed="10" numLanes="1" id="edge_131" /><edge from="castlebar" to="monaghan" length="1619.7197288419993" speed="10" numLanes="1" id="edge_132" /><edge from="navan" to="bray" length="648.9992295835181" speed="10" numLanes="1" id="edge_133" /><edge from="navan" to="carrick" length="1032.4727599312246" speed="10" numLanes="1" id="edge_134" /><edge from="navan" to="derry" length="1745.8593872359825" speed="10" numLanes="1" id="edge_135" /><edge from="navan" to="antrim" length="1303.4354606193588" speed="10" numLanes="1" id="edge_136" /><edge from="navan" to="castlebar" length="1802.725991380831" speed="10" numLanes="1" id="edge_137" /><edge from="monaghan" to="omagh" length="460.3009884847088" speed="10" numLanes="1" id="edge_138" /><edge from="monaghan" to="carlow" length="1814.6616764565233" speed="10" numLanes="1" id="edge_139" /><edge from="monaghan" to="galway" length="1830.0781404082177" speed="10" numLanes="1" id="edge_140" /><edge from="monaghan" to="antrim" length="694.5077393377269" speed="10" numLanes="1" id="edge_141" /><edge from="tullamore" to="cork" length="1891.0975649077443" speed="10" numLanes="1" id="edge_142" /><edge from="tullamore" to="omagh" length="1636.122244821578" speed="10" numLanes="1" id="edge_143" /><edge from="tullamore" to="derry" length="2156.1022703016665" speed="10" numLanes="1" id="edge_144" /><edge from="tullamore" to="sligo" length="1423.0801101835414" speed="10" numLanes="1" id="edge_145" /><edge from="tullamore" to="bray" length="858.3891891211119" speed="10" numLanes="1" id="edge_146" /><edge from="tullamore" to="castlebar" length="1477.81629440198" speed="10" numLanes="1" id="edge_147" /><edge from="tullamore" to="limerick" length="1141.862075734193" speed="10" numLanes="1" id="edge_148" /><edge from="tullamore" to="craigavon" length="1540.397675926577" speed="10" numLanes="1" id="edge_149" /><edge from="tullamore" to="letterkenny" length="2095.2558316348864" speed="10" numLanes="1" id="edge_150" /><edge from="tullamore" to="antrim" length="1896.341741353599" speed="10" numLanes="1" id="edge_151" /><edge from="roscommon" to="antrim" length="1769.962993963433" speed="10" numLanes="1" id="edge_152" /><edge from="roscommon" to="tullamore" length="739.5518913504312" speed="10" numLanes="1" id="edge_153" /><edge from="roscommon" to="naas" length="1203.6760361492622" speed="10" numLanes="1" id="edge_154" /><edge from="roscommon" to="longford" length="321.8400223713639" speed="10" numLanes="1" id="edge_155" /><edge from="roscommon" to="belfast" length="1842.3517579441773" speed="10" numLanes="1" id="edge_156" /><edge from="roscommon" to="galway" length="752.2300180131075" speed="10" numLanes="1" id="edge_157" /><edge from="roscommon" to="portlaoise" length="1076.0227692758178" speed="10" numLanes="1" id="edge_158" /><edge from="roscommon" to="enniskillen" length="930.686305905486" speed="10" numLanes="1" id="edge_159" /><edge from="sligo" to="cork" length="2956.6293308428094" speed="10" numLanes="3" id="edge_160" /><edge from="sligo" to="derry" length="1181.4609599982557" speed="10" numLanes="1" id="edge_161" /><edge from="sligo" to="athlone" length="1065.0938925747344" speed="10" numLanes="1" id="edge_162" /><edge from="sligo" to="antrim" length="1507.3781874499844" speed="10" numLanes="1" id="edge_163" /><edge from="sligo" to="bray" length="2035.171982904639" speed="10" numLanes="1" id="edge_164" /><edge from="sligo" to="tullamore" length="1423.0801101835414" speed="10" numLanes="1" id="edge_165" /><edge from="clonmel" to="craigavon" length="2662.2781597721905" speed="10" numLanes="2" id="edge_166" /><edge from="clonmel" to="sligo" length="2400.582637611128" speed="10" numLanes="1" id="edge_167" /><edge from="clonmel" to="castlebar" length="2132.632410895042" speed="10" numLanes="1" id="edge_168" /><edge from="clonmel" to="kilkenny" length="459.35824799387245" speed="10" numLanes="1" id="edge_169" /><edge from="clonmel" to="carrick" length="1987.944164205826" speed="10" numLanes="1" id="edge_170" /><edge from="clonmel" to="enniskillen" length="2452.9989808395762" speed="10" numLanes="1" id="edge_171" /><edge from="clonmel" to="navan" length="1738.5862072385137" speed="10" numLanes="1" id="edge_172" /><edge from="omagh" to="carrick" length="917.9629622157966" speed="10" numLanes="1" id="edge_173" /><edge from="omagh" to="ennis" length="2433.2950910236923" speed="10" numLanes="2" id="edge_174" /><edge from="omagh" to="kilkenny" length="2405.201031099064" speed="10" numLanes="2" id="edge_175" /><edge from="omagh" to="tralee" length="3295.1062198357126" speed="10" numLanes="1" id="edge_176" /><edge from="omagh" to="longford" length="1075.6625865019198" speed="10" numLanes="1" id="edge_177" /><edge from="omagh" to="dundalk" length="968.2902457424633" speed="10" numLanes="1" id="edge_178" /><edge from="omagh" to="sligo" length="838.32034449845" speed="10" numLanes="1" id="edge_179" /><edge from="omagh" to="monaghan" length="460.3009884847088" speed="10" numLanes="1" id="edge_180" /><edge from="omagh" to="letterkenny" length="517.4176262942731" speed="10" numLanes="1" id="edge_181" /><edge from="waterford" to="navan" length="1780.5897899291683" speed="10" numLanes="1" id="edge_182" /><edge from="waterford" to="belfast" length="2997.61321721132" speed="10" numLanes="1" id="edge_183" /><edge from="waterford" to="roscommon" length="1943.9971707798343" speed="10" numLanes="1" id="edge_184" /><edge from="waterford" to="limerick" length="1188.821685535724" speed="10" numLanes="1" id="edge_185" /><edge from="athlone" to="letterkenny" length="1847.1938176596414" speed="10" numLanes="1" id="edge_186" /><edge from="athlone" to="tullamore" length="408.96454614061594" speed="10" numLanes="1" id="edge_187" /><edge from="athlone" to="clonmel" length="1357.1447969910948" speed="10" numLanes="1" id="edge_188" /><edge from="athlone" to="belfast" length="1870.7658859408357" speed="10" numLanes="1" id="edge_189" /><edge from="athlone" to="enniskillen" length="1118.8395774193903" speed="10" numLanes="1" id="edge_190" /><edge from="athlone" to="carlow" length="1029.49793588914" speed="10" numLanes="1" id="edge_191" /><edge from="wexford" to="ennis" length="1865.080427220231" speed="10" numLanes="1" id="edge_192" /><edge from="wexford" to="galway" length="2118.1314878921" speed="10" numLanes="1" id="edge_193" /><edge from="wexford" to="enniskillen" length="2618.3250371181957" speed="10" numLanes="1" id="edge_194" /><edge from="wexford" to="dundalk" length="2069.0543733792983" speed="10" numLanes="1" id="edge_195" /><edge from="wexford" to="omagh" length="2867.8214728256708" speed="10" numLanes="1" id="edge_196" /><edge from="bray" to="letterkenny" length="2410.606770089224" speed="10" numLanes="1" id="edge_197" /><edge from="bray" to="cavan" length="1232.1047033430236" speed="10" numLanes="1" id="edge_198" /><edge from="bray" to="cork" length="2327.8921796337563" speed="10" numLanes="1" id="edge_199" /><edge from="bray" to="tralee" length="2713.584529731845" speed="10" numLanes="1" id="edge_200" /><edge from="bray" to="tullamore" length="858.3891891211119" speed="10" numLanes="1" id="edge_201" /></edges>